README.md
setup.py
todoist_colors/__init__.py
todoist_colors.egg-info/PKG-INFO
todoist_colors.egg-info/SOURCES.txt
todoist_colors.egg-info/dependency_links.txt
todoist_colors.egg-info/top_level.txt