Metadata-Version: 2.1
Name: todoist-colors
Version: 1.0.1
Summary: Color aliases for Todoist API.
Home-page: https://github.com/VoIlAlex/todoist-colors
Author: voilalex
Author-email: ilya.vouk@gmail.com
License: MIT
Download-URL: https://github.com/VoIlAlex/todoist-colors/archive/v1.0.1.tar.gz
Keywords: util,alias,todoist
Platform: UNKNOWN
Classifier: Development Status :: 5 - Production/Stable
Classifier: Topic :: Utilities
